MANIFEST.in
RELEASE-VERSION
pavement.py
paver-minilib.zip
setup.py
version.py
geo_util/__init__.py
geo_util.egg-info/PKG-INFO
geo_util.egg-info/SOURCES.txt
geo_util.egg-info/dependency_links.txt
geo_util.egg-info/top_level.txt