Metadata-Version: 1.0
Name: geo-util
Version: 0.3
Summary: Library containing various geomtry classes and functions.
Home-page: https://github.com/wheeler-microfluidics/geo-util
Author: Christian Fobel
Author-email: christian@fobel.net
License: LGPL
Platform: UNKNOWN
